{
  "projects": [
    {
      "host": "dokploy",
      "repoPath": "/app",
      "name": "Autopilot Control Tower container",
      "key": "dokploy:/app"
    },
    {
      "host": "233b25d7bf4b",
      "repoPath": "/openclaw/.openclaw/tmp/Wolfenstein 3D port",
      "name": "Wolfenstein 3D port",
      "key": "233b25d7bf4b:/openclaw/.openclaw/tmp/Wolfenstein 3D port"
    },
    {
      "host": "233b25d7bf4b",
      "repoPath": "/openclaw/.openclaw/tmp/etl-scripting-language",
      "name": "ETL scripting language",
      "key": "233b25d7bf4b:/openclaw/.openclaw/tmp/etl-scripting-language"
    },
    {
      "host": "233b25d7bf4b",
      "repoPath": "/openclaw/.openclaw/tmp/autopilot-control-tower",
      "name": "Autopilot Control Tower workspace",
      "key": "233b25d7bf4b:/openclaw/.openclaw/tmp/autopilot-control-tower"
    },
    {
      "host": "dokploy",
      "repoPath": "/openclaw/.openclaw/tmp/md-to-html-preview",
      "name": "Markdown to HTML converter",
      "key": "dokploy:/openclaw/.openclaw/tmp/md-to-html-preview"
    },
    {
      "host": "dokploy",
      "repoPath": "/openclaw/.openclaw/tmp/trailmix",
      "name": "Trailmix",
      "key": "dokploy:/openclaw/.openclaw/tmp/trailmix"
    }
  ]
}
